[{"TRA":[{"source":"TRAV1a","target":"TRAJ33","value":22},{"source":"TRAV12f","target":"TRAJ25","value":4},{"source":"TRAV38b","target":"TRAJ25","value":3},{"source":"TRAV22aa","target":"TRAJ33","value":3},{"source":"TRAV28b","target":"TRAJ37","value":3},{"source":"TRAVXd","target":"TRAJ28","value":3},{"source":"TRAV33d","target":"TRAJ57","value":2},{"source":"TRAV41a","target":"TRAJ52","value":2},{"source":"TRAV22x","target":"TRAJ9","value":2},{"source":"TRAV26ah","target":"TRAJ28","value":2},{"source":"TRAV21b","target":"TRAJ24","value":2},{"source":"TRAV38b","target":"TRAJ21","value":2},{"source":"TRAV35a","target":"TRAJ52","value":2},{"source":"TRAV12d","target":"TRAJ52","value":2},{"source":"TRAVXg","target":"TRAJ57","value":2},{"source":"TRAVXh","target":"TRAJ22","value":2},{"source":"TRAVXq","target":"TRAJ31","value":2},{"source":"TRAVXp","target":"TRAJ23","value":2},{"source":"TRAV17b","target":"TRAJ21","value":2},{"source":"TRAV25f","target":"TRAJ21","value":2},{"source":"TRAVXg","target":"TRAJ15","value":2},{"source":"TRAV3a","target":"TRAJ35","value":2},{"source":"TRAV10b","target":"TRAJ15","value":2},{"source":"TRAV22o","target":"TRAJ9","value":2},{"source":"TRAVXaa","target":"TRAJ31","value":2},{"source":"TRAV12b","target":"TRAJ31","value":2},{"source":"TRAV22p","target":"TRAJ36","value":2},{"source":"TRAV22d","target":"TRAJ25","value":2},{"source":"TRAV9k","target":"TRAJ15","value":2},{"source":"TRAV2b","target":"TRAJ43","value":2},{"source":"TRAVYg","target":"TRAJ50","value":2},{"source":"TRAV5b","target":"TRAJ45","value":1},{"source":"TRAV3e","target":"TRAJ27","value":1},{"source":"TRAV3e","target":"TRAJ41","value":1},{"source":"TRAV8n","target":"TRAJ21","value":1},{"source":"TRAV3e","target":"TRAJ40","value":1},{"source":"TRAV3e","target":"TRAJ23","value":1},{"source":"TRAV8n","target":"TRAJ57","value":1},{"source":"TRAV8n","target":"TRAJ10","value":1},{"source":"TRAV3e","target":"TRAJ21","value":1},{"source":"TRAV3e","target":"TRAJ10","value":1},{"source":"TRAV3d","target":"TRAJ25","value":1},{"source":"TRAV3c","target":"TRAJ52","value":1},{"source":"TRAV3a","target":"TRAJ8-1","value":1},{"source":"TRAV3e","target":"TRAJ8-2","value":1},{"source":"TRAV8l","target":"TRAJ43","value":1},{"source":"TRAV3g","target":"TRAJ32","value":1},{"source":"TRAV5b","target":"TRAJ43","value":1},{"source":"TRAV5b","target":"TRAJ37","value":1},{"source":"TRAV5b","target":"TRAJ27","value":1},{"source":"TRAV5a","target":"TRAJ2","value":1},{"source":"TRAV5a","target":"TRAJ15","value":1},{"source":"TRAV4c","target":"TRAJ32","value":1},{"source":"TRAV8l","target":"TRAJ15","value":1},{"source":"TRAV8l","target":"TRAJ2","value":1},{"source":"TRAV3a","target":"TRAJ41","value":1},{"source":"TRAV4b","target":"TRAJ5","value":1},{"source":"TRAV4a","target":"TRAJ37","value":1},{"source":"TRAV8l","target":"TRAJ25","value":1},{"source":"TRAV3g","target":"TRAJ4","value":1},{"source":"TRAV3g","target":"TRAJ36","value":1},{"source":"TRAV8l","target":"TRAJ3","value":1},{"source":"TRAV8l","target":"TRAJ42","value":1},{"source":"TRAV10b","target":"TRAJ10","value":1},{"source":"TRAV38d","target":"TRAJ46","value":1},{"source":"TRAV3a","target":"TRAJ27","value":1},{"source":"TRAV2c","target":"TRAJ10","value":1},{"source":"TRAV2g","target":"TRAJ36","value":1},{"source":"TRAV2f","target":"TRAJ5","value":1},{"source":"TRAV2f","target":"TRAJ45","value":1},{"source":"TRAV2f","target":"TRAJ40","value":1},{"source":"TRAV2f","target":"TRAJ37","value":1},{"source":"TRAV2f","target":"TRAJ22","value":1},{"source":"TRAV2f","target":"TRAJ21","value":1},{"source":"TRAV2f","target":"TRAJ15","value":1},{"source":"TRAV2c","target":"TRAJ28","value":1},{"source":"TRAV2b","target":"TRAJ42","value":1},{"source":"TRAV3a","target":"TRAJ24","value":1},{"source":"TRAV2b","target":"TRAJ40","value":1},{"source":"TRAV2b","target":"TRAJ36","value":1},{"source":"TRAV2b","target":"TRAJ34","value":1},{"source":"TRAV2b","target":"TRAJ32","value":1},{"source":"TRAV2b","target":"TRAJ22","value":1},{"source":"TRAV2a","target":"TRAJ10","value":1},{"source":"TRAV29c","target":"TRAJ43","value":1},{"source":"TRAV29c","target":"TRAJ37","value":1},{"source":"TRAV29b","target":"TRAJ40","value":1},{"source":"TRAV2g","target":"TRAJ41","value":1},{"source":"TRAV33a","target":"TRAJ57","value":1},{"source":"TRAV38a","target":"TRAJ41","value":1},{"source":"TRAV38a","target":"TRAJ42","value":1},{"source":"TRAV3a","target":"TRAJ16","value":1},{"source":"TRAV3a","target":"TRAJ15","value":1},{"source":"TRAV38e","target":"TRAJ43","value":1},{"source":"TRAV9e","target":"TRAJ52","value":1},{"source":"TRAV38d","target":"TRAJ40","value":1},{"source":"TRAV38d","target":"TRAJ36","value":1},{"source":"TRAV38c","target":"TRAJ20","value":1},{"source":"TRAV38b","target":"TRAJ52","value":1},{"source":"TRAV38b","target":"TRAJ50","value":1},{"source":"TRAV38b","target":"TRAJ46","value":1},{"source":"TRAV38b","target":"TRAJ45","value":1},{"source":"TRAV38b","target":"TRAJ43","value":1},{"source":"TRAV38b","target":"TRAJ33","value":1},{"source":"TRAV38b","target":"TRAJ32","value":1},{"source":"TRAV38b","target":"TRAJ11","value":1},{"source":"TRAV38a","target":"TRAJ54","value":1},{"source":"TRAV38a","target":"TRAJ50","value":1},{"source":"TRAV38a","target":"TRAJ46","value":1},{"source":"TRAV38a","target":"TRAJ43","value":1},{"source":"TRAV9e","target":"TRAJ15","value":1},{"source":"TRAVXaa","target":"TRAJ22","value":1},{"source":"TRAV9g","target":"TRAJ10","value":1},{"source":"TRAVXz","target":"TRAJ32","value":1},{"source":"TRAVYd","target":"TRAJ21","value":1},{"source":"TRAVYc","target":"TRAJ27","value":1},{"source":"TRAVYb","target":"TRAJ36","value":1},{"source":"TRAVYa","target":"TRAJ41","value":1},{"source":"TRAVYa","target":"TRAJ33","value":1},{"source":"TRAVYa","target":"TRAJ27","value":1},{"source":"TRAVYa","target":"TRAJ18","value":1},{"source":"TRAVXz","target":"TRAJ46","value":1},{"source":"TRAVXz","target":"TRAJ41","value":1},{"source":"TRAVXz","target":"TRAJ25","value":1},{"source":"TRAVXp","target":"TRAJ34","value":1},{"source":"TRAVXs","target":"TRAJ32","value":1},{"source":"TRAVXs","target":"TRAJ3","value":1},{"source":"TRAVXs","target":"TRAJ28","value":1},{"source":"TRAVXs","target":"TRAJ27","value":1},{"source":"TRAVXr","target":"TRAJ22","value":1},{"source":"TRAVXq","target":"TRAJ46","value":1},{"source":"TRAVXq","target":"TRAJ43","value":1},{"source":"TRAVXq","target":"TRAJ4","value":1},{"source":"TRAVXq","target":"TRAJ34","value":1},{"source":"TRAVYd","target":"TRAJ40","value":1},{"source":"TRAVYd","target":"TRAJ45","value":1},{"source":"TRAVYe","target":"TRAJ16","value":1},{"source":"TRAVYe","target":"TRAJ43","value":1},{"source":"TRDV1e","target":"TRAJ52","value":1},{"source":"TRDV1bg","target":"TRAJ25","value":1},{"source":"TRDV1bg","target":"TRAJ21","value":1},{"source":"TRDV1bb","target":"TRAJ40","value":1},{"source":"TRDV1bb","target":"TRAJ15","value":1},{"source":"TRDV1ax","target":"TRAJ8-2","value":1},{"source":"TRDV1ax","target":"TRAJ22","value":1},{"source":"TRDV1aw","target":"TRAJ52","value":1},{"source":"TRDV1ak","target":"TRAJ43","value":1},{"source":"TRDV1aj","target":"TRAJ45","value":1},{"source":"TRDV1aj","target":"TRAJ36","value":1},{"source":"TRDV1aj","target":"TRAJ23","value":1},{"source":"TRDV1aa","target":"TRAJ46","value":1},{"source":"TRAVYg","target":"TRAJ43","value":1},{"source":"TRAVYg","target":"TRAJ42","value":1},{"source":"TRAVYg","target":"TRAJ32","value":1},{"source":"TRAVYg","target":"TRAJ31","value":1},{"source":"TRAVYg","target":"TRAJ22","value":1},{"source":"TRAVYg","target":"TRAJ20","value":1},{"source":"TRAVXq","target":"TRAJ3","value":1},{"source":"TRAVXp","target":"TRAJ2","value":1},{"source":"TRAV9g","target":"TRAJ41","value":1},{"source":"TRAVXaa","target":"TRAJ28","value":1},{"source":"TRAVXac","target":"TRAJ10","value":1},{"source":"TRAVXab","target":"TRAJ5","value":1},{"source":"TRAVXab","target":"TRAJ45","value":1},{"source":"TRAVXab","target":"TRAJ40","value":1},{"source":"TRAVXaa","target":"TRAJ45","value":1},{"source":"TRAVXaa","target":"TRAJ41","value":1},{"source":"TRAVXaa","target":"TRAJ37","value":1},{"source":"TRAVXaa","target":"TRAJ34","value":1},{"source":"TRAVXaa","target":"TRAJ33","value":1},{"source":"TRAVXaa","target":"TRAJ27","value":1},{"source":"TRAVXo","target":"TRAJ23","value":1},{"source":"TRAVXaa","target":"TRAJ25","value":1},{"source":"TRAVXaa","target":"TRAJ23","value":1},{"source":"TRAV29b","target":"TRAJ37","value":1},{"source":"TRAVXaa","target":"TRAJ16","value":1},{"source":"TRAVXaa","target":"TRAJ11","value":1},{"source":"TRAVXaa","target":"TRAJ10","value":1},{"source":"TRAVXa","target":"TRAJ45","value":1},{"source":"TRAVXa","target":"TRAJ3","value":1},{"source":"TRAV9g","target":"TRAJ43","value":1},{"source":"TRAVXac","target":"TRAJ40","value":1},{"source":"TRAVXb","target":"TRAJ16","value":1},{"source":"TRAVXb","target":"TRAJ32","value":1},{"source":"TRAVXc","target":"TRAJ2","value":1},{"source":"TRAVXn","target":"TRAJ52","value":1},{"source":"TRAVXn","target":"TRAJ43","value":1},{"source":"TRAVXn","target":"TRAJ41","value":1},{"source":"TRAVXn","target":"TRAJ34","value":1},{"source":"TRAVXn","target":"TRAJ28","value":1},{"source":"TRAVXm","target":"TRAJ4","value":1},{"source":"TRAVXm","target":"TRAJ32","value":1},{"source":"TRAVXk","target":"TRAJ5","value":1},{"source":"TRAVXk","target":"TRAJ3","value":1},{"source":"TRAVXk","target":"TRAJ10","value":1},{"source":"TRAVXj","target":"TRAJ45","value":1},{"source":"TRAVXj","target":"TRAJ37","value":1},{"source":"TRAVXi","target":"TRAJ23","value":1},{"source":"TRAVXh","target":"TRAJ5","value":1},{"source":"TRAVXh","target":"TRAJ43","value":1},{"source":"TRAVXh","target":"TRAJ23","value":1},{"source":"TRAVXg","target":"TRAJ37","value":1},{"source":"TRAVXg","target":"TRAJ25","value":1},{"source":"TRAVXe","target":"TRAJ15","value":1},{"source":"TRAV29b","target":"TRAJ39","value":1},{"source":"TRAV28b","target":"TRAJ27","value":1},{"source":"TRAV29b","target":"TRAJ34","value":1},{"source":"TRAV19c","target":"TRAJ57","value":1},{"source":"TRAV1a","target":"TRAJ41","value":1},{"source":"TRAV1a","target":"TRAJ40","value":1},{"source":"TRAV1a","target":"TRAJ39","value":1},{"source":"TRAV1a","target":"TRAJ36","value":1},{"source":"TRAV1a","target":"TRAJ34","value":1},{"source":"TRAV1a","target":"TRAJ32","value":1},{"source":"TRAV1a","target":"TRAJ28","value":1},{"source":"TRAV1a","target":"TRAJ27","value":1},{"source":"TRAV19f","target":"TRAJ22","value":1},{"source":"TRAV19a","target":"TRAJ37","value":1},{"source":"TRAV1a","target":"TRAJ50","value":1},{"source":"TRAV19a","target":"TRAJ18","value":1},{"source":"TRAV18b","target":"TRAJ4","value":1},{"source":"TRAV17b","target":"TRAJ22","value":1},{"source":"TRAV17b","target":"TRAJ18","value":1},{"source":"TRAV17a","target":"TRAJ24","value":1},{"source":"TRAV17a","target":"TRAJ15","value":1},{"source":"TRAV16a","target":"TRAJ31","value":1},{"source":"TRAV16a","target":"TRAJ3","value":1},{"source":"TRAV16a","target":"TRAJ21","value":1},{"source":"TRAV1a","target":"TRAJ43","value":1},{"source":"TRAV20e","target":"TRAJ16","value":1},{"source":"TRAV14e","target":"TRAJ50","value":1},{"source":"TRAV22ab","target":"TRAJ37","value":1},{"source":"TRAV22d","target":"TRAJ43","value":1},{"source":"TRAV22d","target":"TRAJ4","value":1},{"source":"TRAV22b","target":"TRAJ8-2","value":1},{"source":"TRAV22b","target":"TRAJ45","value":1},{"source":"TRAV22b","target":"TRAJ34","value":1},{"source":"TRAV22b","target":"TRAJ2","value":1},{"source":"TRAV22ab","target":"TRAJ8-2","value":1},{"source":"TRAV22ab","target":"TRAJ5","value":1},{"source":"TRAV22ab","target":"TRAJ45","value":1},{"source":"TRAV22aa","target":"TRAJ53","value":1},{"source":"TRAV20e","target":"TRAJ52","value":1},{"source":"TRAV22aa","target":"TRAJ45","value":1},{"source":"TRAV22aa","target":"TRAJ37","value":1},{"source":"TRAV22aa","target":"TRAJ31","value":1},{"source":"TRAV22aa","target":"TRAJ22","value":1},{"source":"TRAV22aa","target":"TRAJ21","value":1},{"source":"TRAV22a","target":"TRAJ45","value":1},{"source":"TRAV22a","target":"TRAJ3","value":1},{"source":"TRAV21b","target":"TRAJ4","value":1},{"source":"TRAV21b","target":"TRAJ11","value":1},{"source":"TRAV14g","target":"TRAJ21","value":1},{"source":"TRAV14e","target":"TRAJ4","value":1},{"source":"TRAV29b","target":"TRAJ33","value":1},{"source":"TRAV12c","target":"TRAJ23","value":1},{"source":"TRAV12d","target":"TRAJ9","value":1},{"source":"TRAV12d","target":"TRAJ54","value":1},{"source":"TRAV12d","target":"TRAJ50","value":1},{"source":"TRAV12d","target":"TRAJ4","value":1},{"source":"TRAV12d","target":"TRAJ32","value":1},{"source":"TRAV12d","target":"TRAJ22","value":1},{"source":"TRAV12d","target":"TRAJ11","value":1},{"source":"TRAV12c","target":"TRAJ57","value":1},{"source":"TRAV12c","target":"TRAJ37","value":1},{"source":"TRAV12c","target":"TRAJ15","value":1},{"source":"TRAV12f","target":"TRAJ21","value":1},{"source":"TRAV12b","target":"TRAJ50","value":1},{"source":"TRAV12b","target":"TRAJ42","value":1},{"source":"TRAV12b","target":"TRAJ40","value":1},{"source":"TRAV12a","target":"TRAJ52","value":1},{"source":"TRAV12a","target":"TRAJ24","value":1},{"source":"TRAV10d","target":"TRAJ33","value":1},{"source":"TRAV10b","target":"TRAJ50","value":1},{"source":"TRAV10b","target":"TRAJ23","value":1},{"source":"TRAV10b","target":"TRAJ18","value":1},{"source":"TRAV12f","target":"TRAJ16","value":1},{"source":"TRAV12f","target":"TRAJ40","value":1},{"source":"TRAV14e","target":"TRAJ18","value":1},{"source":"TRAV13e","target":"TRAJ43","value":1},{"source":"TRAV14e","target":"TRAJ10","value":1},{"source":"TRAV14d","target":"TRAJ41","value":1},{"source":"TRAV14c","target":"TRAJ50","value":1},{"source":"TRAV14c","target":"TRAJ15","value":1},{"source":"TRAV13j","target":"TRAJ46","value":1},{"source":"TRAV13j","target":"TRAJ22","value":1},{"source":"TRAV13j","target":"TRAJ2","value":1},{"source":"TRAV13h","target":"TRAJ23","value":1},{"source":"TRAV13e","target":"TRAJ50","value":1},{"source":"TRAV13e","target":"TRAJ32","value":1},{"source":"TRAV12f","target":"TRAJ45","value":1},{"source":"TRAV13b","target":"TRAJ46","value":1},{"source":"TRAV13b","target":"TRAJ45","value":1},{"source":"TRAV13b","target":"TRAJ40","value":1},{"source":"TRAV13b","target":"TRAJ32","value":1},{"source":"TRAV13b","target":"TRAJ31","value":1},{"source":"TRAV13b","target":"TRAJ21","value":1},{"source":"TRAV13b","target":"TRAJ10","value":1},{"source":"TRAV12f","target":"TRAJ8-2","value":1},{"source":"TRAV12f","target":"TRAJ50","value":1},{"source":"TRAV22f","target":"TRAJ38","value":1},{"source":"TRAV22f","target":"TRAJ4","value":1},{"source":"TRAV22h","target":"TRAJ28","value":1},{"source":"TRAV26ad","target":"TRAJ33","value":1},{"source":"TRAV26am","target":"TRAJ25","value":1},{"source":"TRAV26aj","target":"TRAJ53","value":1},{"source":"TRAV26aj","target":"TRAJ41","value":1},{"source":"TRAV26ai","target":"TRAJ24","value":1},{"source":"TRAV26ai","target":"TRAJ20","value":1},{"source":"TRAV26ai","target":"TRAJ11","value":1},{"source":"TRAV26ah","target":"TRAJ16","value":1},{"source":"TRAV26ae","target":"TRAJ33","value":1},{"source":"TRAV26ae","target":"TRAJ15","value":1},{"source":"TRAV26ac","target":"TRAJ37","value":1},{"source":"TRAV26i","target":"TRAJ22","value":1},{"source":"TRAV25v","target":"TRAJ27","value":1},{"source":"TRAV25v","target":"TRAJ20","value":1},{"source":"TRAV25u","target":"TRAJ37","value":1},{"source":"TRAV25u","target":"TRAJ2","value":1},{"source":"TRAV25u","target":"TRAJ18","value":1},{"source":"TRAV25u","target":"TRAJ15","value":1},{"source":"TRAV25r","target":"TRAJ43","value":1},{"source":"TRAV25p","target":"TRAJ50","value":1},{"source":"TRAV25p","target":"TRAJ44","value":1},{"source":"TRAV26i","target":"TRAJ16","value":1},{"source":"TRAV26i","target":"TRAJ36","value":1},{"source":"TRAV22h","target":"TRAJ33","value":1},{"source":"TRAV28a","target":"TRAJ21","value":1},{"source":"TRAV28b","target":"TRAJ8-2","value":1},{"source":"TRAV28b","target":"TRAJ45","value":1},{"source":"TRAV28b","target":"TRAJ43","value":1},{"source":"TRAV28b","target":"TRAJ33","value":1},{"source":"TRAV10b","target":"TRAJ11","value":1},{"source":"TRAV28b","target":"TRAJ23","value":1},{"source":"TRAV28b","target":"TRAJ22","value":1},{"source":"TRAV28a","target":"TRAJ43","value":1},{"source":"TRAV28a","target":"TRAJ37","value":1},{"source":"TRAV27a","target":"TRAJ32","value":1},{"source":"TRAV26i","target":"TRAJ43","value":1},{"source":"TRAV27a","target":"TRAJ27","value":1},{"source":"TRAV26w","target":"TRAJ4","value":1},{"source":"TRAV26u","target":"TRAJ38","value":1},{"source":"TRAV26u","target":"TRAJ36","value":1},{"source":"TRAV26u","target":"TRAJ28","value":1},{"source":"TRAV26u","target":"TRAJ27","value":1},{"source":"TRAV26u","target":"TRAJ15","value":1},{"source":"TRAV26k","target":"TRAJ45","value":1},{"source":"TRAV26k","target":"TRAJ40","value":1},{"source":"TRAV25p","target":"TRAJ24","value":1},{"source":"TRAV25p","target":"TRAJ20","value":1},{"source":"TRAV25o","target":"TRAJ34","value":1},{"source":"TRAV22q","target":"TRAJ22","value":1},{"source":"TRAV22w","target":"TRAJ28","value":1},{"source":"TRAV22w","target":"TRAJ27","value":1},{"source":"TRAV22w","target":"TRAJ2","value":1},{"source":"TRAV22t","target":"TRAJ54","value":1},{"source":"TRAV22t","target":"TRAJ45","value":1},{"source":"TRAV22t","target":"TRAJ41","value":1},{"source":"TRAV22t","target":"TRAJ32","value":1},{"source":"TRAV22t","target":"TRAJ15","value":1},{"source":"TRAV22q","target":"TRAJ23","value":1},{"source":"TRAV22q","target":"TRAJ15","value":1},{"source":"TRAV25l","target":"TRAJ21","value":1},{"source":"TRAV22p","target":"TRAJ21","value":1},{"source":"TRAV22p","target":"TRAJ15","value":1},{"source":"TRAV22o","target":"TRAJ39","value":1},{"source":"TRAV22o","target":"TRAJ24","value":1},{"source":"TRAV22o","target":"TRAJ23","value":1},{"source":"TRAV22n","target":"TRAJ22","value":1},{"source":"TRAV22n","target":"TRAJ20","value":1},{"source":"TRAV22l","target":"TRAJ18","value":1},{"source":"TRAV22h","target":"TRAJ39","value":1},{"source":"TRAV22w","target":"TRAJ36","value":1},{"source":"TRAV22x","target":"TRAJ22","value":1},{"source":"TRAV22x","target":"TRAJ5","value":1},{"source":"TRAV22x","target":"TRAJ54","value":1},{"source":"TRAV25f","target":"TRAJ37","value":1},{"source":"TRAV25f","target":"TRAJ15","value":1},{"source":"TRAV25d","target":"TRAJ32","value":1},{"source":"TRAV25b","target":"TRAJ52","value":1},{"source":"TRAV25b","target":"TRAJ50","value":1},{"source":"TRAV25b","target":"TRAJ43","value":1},{"source":"TRAV25b","target":"TRAJ41","value":1},{"source":"TRAV25b","target":"TRAJ33","value":1},{"source":"TRAV25b","target":"TRAJ23","value":1},{"source":"TRAV23x","target":"TRAJ5","value":1},{"source":"TRAV23x","target":"TRAJ28","value":1},{"source":"TRAV23x","target":"TRAJ27","value":1},{"source":"TRAV23x","target":"TRAJ21","value":1},{"source":"TRAV23x","target":"TRAJ18","value":1},{"source":"TRAV23t","target":"TRAJ22","value":1},{"source":"TRAV22z","target":"TRAJ37","value":1},{"source":"TRAV22z","target":"TRAJ22","value":1},{"source":"TRAV22x","target":"TRAJ8-1","value":1},{"source":"TRAV22x","target":"TRAJ57","value":1},{"source":"TRDV1w","target":"TRAJ27","value":1}],"TRAGene":[{"name":"TRAV1a"},{"name":"TRAV12f"},{"name":"TRAV38b"},{"name":"TRAV22aa"},{"name":"TRAV28b"},{"name":"TRAVXd"},{"name":"TRAV33d"},{"name":"TRAV41a"},{"name":"TRAV22x"},{"name":"TRAV26ah"},{"name":"TRAV21b"},{"name":"TRAV35a"},{"name":"TRAV12d"},{"name":"TRAVXg"},{"name":"TRAVXh"},{"name":"TRAVXq"},{"name":"TRAVXp"},{"name":"TRAV17b"},{"name":"TRAV25f"},{"name":"TRAV3a"},{"name":"TRAV10b"},{"name":"TRAV22o"},{"name":"TRAVXaa"},{"name":"TRAV12b"},{"name":"TRAV22p"},{"name":"TRAV22d"},{"name":"TRAV9k"},{"name":"TRAV2b"},{"name":"TRAVYg"},{"name":"TRAV5b"},{"name":"TRAV3e"},{"name":"TRAV8n"},{"name":"TRAV3d"},{"name":"TRAV3c"},{"name":"TRAV8l"},{"name":"TRAV3g"},{"name":"TRAV5a"},{"name":"TRAV4c"},{"name":"TRAV4b"},{"name":"TRAV4a"},{"name":"TRAV38d"},{"name":"TRAV2c"},{"name":"TRAV2g"},{"name":"TRAV2f"},{"name":"TRAV2a"},{"name":"TRAV29c"},{"name":"TRAV29b"},{"name":"TRAV33a"},{"name":"TRAV38a"},{"name":"TRAV38e"},{"name":"TRAV9e"},{"name":"TRAV38c"},{"name":"TRAV9g"},{"name":"TRAVXz"},{"name":"TRAVYd"},{"name":"TRAVYc"},{"name":"TRAVYb"},{"name":"TRAVYa"},{"name":"TRAVXs"},{"name":"TRAVXr"},{"name":"TRAVYe"},{"name":"TRDV1e"},{"name":"TRDV1bg"},{"name":"TRDV1bb"},{"name":"TRDV1ax"},{"name":"TRDV1aw"},{"name":"TRDV1ak"},{"name":"TRDV1aj"},{"name":"TRDV1aa"},{"name":"TRAVXac"},{"name":"TRAVXab"},{"name":"TRAVXo"},{"name":"TRAVXa"},{"name":"TRAVXb"},{"name":"TRAVXc"},{"name":"TRAVXn"},{"name":"TRAVXm"},{"name":"TRAVXk"},{"name":"TRAVXj"},{"name":"TRAVXi"},{"name":"TRAVXe"},{"name":"TRAV19c"},{"name":"TRAV19f"},{"name":"TRAV19a"},{"name":"TRAV18b"},{"name":"TRAV17a"},{"name":"TRAV16a"},{"name":"TRAV20e"},{"name":"TRAV14e"},{"name":"TRAV22ab"},{"name":"TRAV22b"},{"name":"TRAV22a"},{"name":"TRAV14g"},{"name":"TRAV12c"},{"name":"TRAV12a"},{"name":"TRAV10d"},{"name":"TRAV13e"},{"name":"TRAV14d"},{"name":"TRAV14c"},{"name":"TRAV13j"},{"name":"TRAV13h"},{"name":"TRAV13b"},{"name":"TRAV22f"},{"name":"TRAV22h"},{"name":"TRAV26ad"},{"name":"TRAV26am"},{"name":"TRAV26aj"},{"name":"TRAV26ai"},{"name":"TRAV26ae"},{"name":"TRAV26ac"},{"name":"TRAV26i"},{"name":"TRAV25v"},{"name":"TRAV25u"},{"name":"TRAV25r"},{"name":"TRAV25p"},{"name":"TRAV28a"},{"name":"TRAV27a"},{"name":"TRAV26w"},{"name":"TRAV26u"},{"name":"TRAV26k"},{"name":"TRAV25o"},{"name":"TRAV22q"},{"name":"TRAV22w"},{"name":"TRAV22t"},{"name":"TRAV25l"},{"name":"TRAV22n"},{"name":"TRAV22l"},{"name":"TRAV25d"},{"name":"TRAV25b"},{"name":"TRAV23x"},{"name":"TRAV23t"},{"name":"TRAV22z"},{"name":"TRDV1w"},{"name":"TRAJ33"},{"name":"TRAJ25"},{"name":"TRAJ37"},{"name":"TRAJ28"},{"name":"TRAJ57"},{"name":"TRAJ52"},{"name":"TRAJ9"},{"name":"TRAJ24"},{"name":"TRAJ21"},{"name":"TRAJ22"},{"name":"TRAJ31"},{"name":"TRAJ23"},{"name":"TRAJ15"},{"name":"TRAJ35"},{"name":"TRAJ36"},{"name":"TRAJ43"},{"name":"TRAJ50"},{"name":"TRAJ45"},{"name":"TRAJ27"},{"name":"TRAJ41"},{"name":"TRAJ40"},{"name":"TRAJ10"},{"name":"TRAJ8-1"},{"name":"TRAJ8-2"},{"name":"TRAJ32"},{"name":"TRAJ2"},{"name":"TRAJ5"},{"name":"TRAJ4"},{"name":"TRAJ3"},{"name":"TRAJ42"},{"name":"TRAJ46"},{"name":"TRAJ34"},{"name":"TRAJ16"},{"name":"TRAJ20"},{"name":"TRAJ11"},{"name":"TRAJ54"},{"name":"TRAJ18"},{"name":"TRAJ39"},{"name":"TRAJ53"},{"name":"TRAJ38"},{"name":"TRAJ44"}],"sumTRA":453,"TRB":[{"source":"TRBV4a","target":"TRBJ3.3","value":65},{"source":"TRBV20c","target":"TRBJ3.2","value":65},{"source":"TRBV4a","target":"TRBJ3.7","value":56},{"source":"TRBV4a","target":"TRBJ2.1","value":53},{"source":"TRBV4a","target":"TRBJ3.2","value":51},{"source":"TRBV20c","target":"TRBJ3.3","value":49},{"source":"TRBV4a","target":"TRBJ3.4","value":42},{"source":"TRBV20b","target":"TRBJ3.2","value":36},{"source":"TRBV4a","target":"TRBJ1.1","value":33},{"source":"TRBV7a","target":"TRBJ3.2","value":33},{"source":"TRBV20b","target":"TRBJ3.3","value":30},{"source":"TRBV20d","target":"TRBJ3.3","value":28},{"source":"TRBV7a","target":"TRBJ3.4","value":27},{"source":"TRBV4a","target":"TRBJ3.5","value":25},{"source":"TRBV4a","target":"TRBJ2.3","value":25},{"source":"TRBV20a","target":"TRBJ3.3","value":25},{"source":"TRBV26a","target":"TRBJ3.4","value":19},{"source":"TRBV20c","target":"TRBJ1.5","value":16},{"source":"TRBV7a","target":"TRBJ3.3","value":16},{"source":"TRBV20a","target":"TRBJ3.2","value":16},{"source":"TRBV4a","target":"TRBJ2.2","value":16},{"source":"TRBV29b","target":"TRBJ3.4","value":16},{"source":"TRBV4a","target":"TRBJ2.5","value":15},{"source":"TRBV6b","target":"TRBJ3.3","value":15},{"source":"TRBV20b","target":"TRBJ2.1","value":15},{"source":"TRBV20b","target":"TRBJ2.4","value":15},{"source":"TRBV20c","target":"TRBJ3.4","value":15},{"source":"TRBV29b","target":"TRBJ3.2","value":14},{"source":"TRBV20b","target":"TRBJ3.4","value":14},{"source":"TRBV29b","target":"TRBJ3.3","value":14},{"source":"TRBV4a","target":"TRBJ1.5","value":13},{"source":"TRBV30a","target":"TRBJ3.3","value":12},{"source":"TRBV20b","target":"TRBJ1.5","value":11},{"source":"TRBV4a","target":"TRBJ2.4","value":11},{"source":"TRBV7a","target":"TRBJ2.1","value":11},{"source":"TRBV20b","target":"TRBJ3.7","value":11},{"source":"TRBV4b","target":"TRBJ3.3","value":10},{"source":"TRBV19d","target":"TRBJ3.3","value":10},{"source":"TRBV29b","target":"TRBJ1.5","value":10},{"source":"TRBV29b","target":"TRBJ2.3","value":10},{"source":"TRBV20a","target":"TRBJ1.5","value":10},{"source":"TRBV7a","target":"TRBJ3.7","value":10},{"source":"TRBV20c","target":"TRBJ3.7","value":10},{"source":"TRBV6b","target":"TRBJ3.7","value":10},{"source":"TRBV6ac","target":"TRBJ3.4","value":10},{"source":"TRBV6ac","target":"TRBJ3.5","value":10},{"source":"TRBV29e","target":"TRBJ3.2","value":9},{"source":"TRBV20c","target":"TRBJ3.5","value":9},{"source":"TRBV6ac","target":"TRBJ3.7","value":9},{"source":"TRBVXa","target":"TRBJ3.7","value":9},{"source":"TRBV15a","target":"TRBJ3.2","value":9},{"source":"TRBV15a","target":"TRBJ3.5","value":9},{"source":"TRBV30a","target":"TRBJ2.1","value":8},{"source":"TRBV26a","target":"TRBJ3.7","value":8},{"source":"TRBV20c","target":"TRBJ2.4","value":8},{"source":"TRBV29d","target":"TRBJ3.3","value":8},{"source":"TRBV20a","target":"TRBJ3.4","value":8},{"source":"TRBV26a","target":"TRBJ3.2","value":8},{"source":"TRBV7a","target":"TRBJ3.5","value":8},{"source":"TRBV20c","target":"TRBJ2.1","value":7},{"source":"TRBV20d","target":"TRBJ3.7","value":7},{"source":"TRBV30a","target":"TRBJ3.4","value":7},{"source":"TRBV29d","target":"TRBJ3.4","value":7},{"source":"TRBV29b","target":"TRBJ3.5","value":7},{"source":"TRBV26a","target":"TRBJ3.3","value":7},{"source":"TRBV19d","target":"TRBJ3.2","value":7},{"source":"TRBV15a","target":"TRBJ3.3","value":7},{"source":"TRBV4b","target":"TRBJ3.4","value":7},{"source":"TRBV20b","target":"TRBJ2.3","value":7},{"source":"TRBV26a","target":"TRBJ3.5","value":7},{"source":"TRBV29e","target":"TRBJ3.4","value":7},{"source":"TRBV20d","target":"TRBJ3.2","value":7},{"source":"TRBV6i","target":"TRBJ3.7","value":7},{"source":"TRBV30a","target":"TRBJ3.7","value":6},{"source":"TRBVXa","target":"TRBJ1.5","value":6},{"source":"TRBV6i","target":"TRBJ2.4","value":6},{"source":"TRBV29e","target":"TRBJ1.1","value":6},{"source":"TRBV7a","target":"TRBJ2.4","value":6},{"source":"TRBV6ac","target":"TRBJ2.3","value":6},{"source":"TRBV4b","target":"TRBJ3.7","value":6},{"source":"TRBV29e","target":"TRBJ3.5","value":6},{"source":"TRBV20a","target":"TRBJ1.1","value":6},{"source":"TRBV20a","target":"TRBJ3.7","value":6},{"source":"TRBV6i","target":"TRBJ2.1","value":6},{"source":"TRBV26a","target":"TRBJ2.5","value":5},{"source":"TRBV7a","target":"TRBJ2.2","value":5},{"source":"TRBV20d","target":"TRBJ3.4","value":5},{"source":"TRBV26a","target":"TRBJ2.4","value":5},{"source":"TRBV21d","target":"TRBJ3.7","value":5},{"source":"TRBV6ac","target":"TRBJ3.2","value":5},{"source":"TRBV29b","target":"TRBJ2.1","value":5},{"source":"TRBV6ah","target":"TRBJ3.3","value":5},{"source":"TRBV20c","target":"TRBJ1.1","value":5},{"source":"TRBV20a","target":"TRBJ2.1","value":5},{"source":"TRBV30a","target":"TRBJ2.3","value":5},{"source":"TRBV29e","target":"TRBJ3.7","value":5},{"source":"TRBV20b","target":"TRBJ1.1","value":5},{"source":"TRBV29e","target":"TRBJ2.3","value":5},{"source":"TRBV3a","target":"TRBJ3.4","value":5},{"source":"TRBV29e","target":"TRBJ1.5","value":5},{"source":"TRBV29d","target":"TRBJ2.1","value":4},{"source":"TRBV6i","target":"TRBJ3.4","value":4},{"source":"TRBV13al","target":"TRBJ3.4","value":4},{"source":"TRBV26a","target":"TRBJ2.3","value":4},{"source":"TRBVXa","target":"TRBJ3.2","value":4},{"source":"TRBV7b","target":"TRBJ3.7","value":4},{"source":"TRBV29e","target":"TRBJ3.3","value":4},{"source":"TRBV6m","target":"TRBJ3.4","value":4},{"source":"TRBV9a","target":"TRBJ3.4","value":4},{"source":"TRBV6ac","target":"TRBJ1.1","value":4},{"source":"TRBV15a","target":"TRBJ3.4","value":4},{"source":"TRBV9ae","target":"TRBJ3.1","value":4},{"source":"TRBV29b","target":"TRBJ1.1","value":4},{"source":"TRBV9ae","target":"TRBJ3.2","value":4},{"source":"TRBV24a","target":"TRBJ2.1","value":4},{"source":"TRBV6r","target":"TRBJ3.2","value":4},{"source":"TRBV19b","target":"TRBJ3.3","value":4},{"source":"TRBV6i","target":"TRBJ3.2","value":4},{"source":"TRBV6ac","target":"TRBJ3.3","value":4},{"source":"TRBV20b","target":"TRBJ3.5","value":4},{"source":"TRBV6i","target":"TRBJ3.3","value":4},{"source":"TRBV19d","target":"TRBJ2.4","value":4},{"source":"TRBV6m","target":"TRBJ3.2","value":3},{"source":"TRBV29b","target":"TRBJ1.3","value":3},{"source":"TRBV6b","target":"TRBJ3.2","value":3},{"source":"TRBV12b","target":"TRBJ3.7","value":3},{"source":"TRBV29b","target":"TRBJ2.4","value":3},{"source":"TRBV19b","target":"TRBJ3.4","value":3},{"source":"TRBV6r","target":"TRBJ1.1","value":3},{"source":"TRBVXa","target":"TRBJ2.1","value":3},{"source":"TRBV12b","target":"TRBJ3.4","value":3},{"source":"TRBV6r","target":"TRBJ3.3","value":3},{"source":"TRBV20c","target":"TRBJ2.3","value":3},{"source":"TRBV21h","target":"TRBJ2.1","value":3},{"source":"TRBV29b","target":"TRBJ3.7","value":3},{"source":"TRBV9aa","target":"TRBJ2.1","value":3},{"source":"TRBVXa","target":"TRBJ2.3","value":3},{"source":"TRBV6m","target":"TRBJ3.7","value":3},{"source":"TRBV20c","target":"TRBJ2.2","value":3},{"source":"TRBV19d","target":"TRBJ3.5","value":3},{"source":"TRBV4a","target":"TRBJ1.3","value":3},{"source":"TRBV12b","target":"TRBJ2.1","value":3},{"source":"TRBV3a","target":"TRBJ3.7","value":3},{"source":"TRBV29d","target":"TRBJ3.2","value":3},{"source":"TRBV6b","target":"TRBJ3.4","value":3},{"source":"TRBV29d","target":"TRBJ3.7","value":3},{"source":"TRBV19d","target":"TRBJ2.2","value":3},{"source":"TRBV29e","target":"TRBJ1.3","value":3},{"source":"TRBV20b","target":"TRBJ2.5","value":3},{"source":"TRBV19d","target":"TRBJ3.4","value":3},{"source":"TRBV20a","target":"TRBJ3.5","value":3},{"source":"TRBV13al","target":"TRBJ3.7","value":3},{"source":"TRBV4b","target":"TRBJ3.2","value":3},{"source":"TRBV9ae","target":"TRBJ2.1","value":3},{"source":"TRBV20a","target":"TRBJ2.4","value":3},{"source":"TRBV21d","target":"TRBJ3.4","value":3},{"source":"TRBV21d","target":"TRBJ3.3","value":3},{"source":"TRBV21d","target":"TRBJ3.2","value":3},{"source":"TRBV6b","target":"TRBJ2.1","value":3},{"source":"TRBV6ac","target":"TRBJ2.2","value":3},{"source":"TRBV4b","target":"TRBJ3.5","value":3},{"source":"TRBV6ac","target":"TRBJ2.4","value":3},{"source":"TRBV30a","target":"TRBJ3.2","value":3},{"source":"TRBV7b","target":"TRBJ3.3","value":3},{"source":"TRBV3a","target":"TRBJ3.2","value":3},{"source":"TRBV30a","target":"TRBJ2.4","value":3},{"source":"TRBV6m","target":"TRBJ1.5","value":3},{"source":"TRBV26a","target":"TRBJ2.1","value":3},{"source":"TRBV26a","target":"TRBJ2.2","value":3},{"source":"TRBV6ad","target":"TRBJ3.3","value":3},{"source":"TRBV6b","target":"TRBJ2.4","value":3},{"source":"TRBV7b","target":"TRBJ3.5","value":3},{"source":"TRBV6r","target":"TRBJ3.7","value":3},{"source":"TRBV6b","target":"TRBJ2.5","value":3},{"source":"TRBV6r","target":"TRBJ3.5","value":3},{"source":"TRBV6r","target":"TRBJ3.4","value":3},{"source":"TRBV30a","target":"TRBJ1.5","value":3},{"source":"TRBV20d","target":"TRBJ1.1","value":3},{"source":"TRBV21h","target":"TRBJ3.3","value":3},{"source":"TRBV6w","target":"TRBJ3.7","value":3}],"TRBGene":[{"name":"TRBV4a"},{"name":"TRBV20c"},{"name":"TRBV20b"},{"name":"TRBV7a"},{"name":"TRBV20d"},{"name":"TRBV20a"},{"name":"TRBV26a"},{"name":"TRBV29b"},{"name":"TRBV6b"},{"name":"TRBV30a"},{"name":"TRBV4b"},{"name":"TRBV19d"},{"name":"TRBV6ac"},{"name":"TRBV29e"},{"name":"TRBVXa"},{"name":"TRBV15a"},{"name":"TRBV29d"},{"name":"TRBV6i"},{"name":"TRBV21d"},{"name":"TRBV6ah"},{"name":"TRBV3a"},{"name":"TRBV13al"},{"name":"TRBV7b"},{"name":"TRBV6m"},{"name":"TRBV9a"},{"name":"TRBV9ae"},{"name":"TRBV24a"},{"name":"TRBV6r"},{"name":"TRBV19b"},{"name":"TRBV12b"},{"name":"TRBV21h"},{"name":"TRBV9aa"},{"name":"TRBV6ad"},{"name":"TRBV6w"},{"name":"TRBJ3.3"},{"name":"TRBJ3.2"},{"name":"TRBJ3.7"},{"name":"TRBJ2.1"},{"name":"TRBJ3.4"},{"name":"TRBJ1.1"},{"name":"TRBJ3.5"},{"name":"TRBJ2.3"},{"name":"TRBJ1.5"},{"name":"TRBJ2.2"},{"name":"TRBJ2.5"},{"name":"TRBJ2.4"},{"name":"TRBJ3.1"},{"name":"TRBJ1.3"}],"sumTRB":1952}]